Metadata-Version: 2.1
Name: urlscrub
Version: 0.1.0
Summary: Tool for parsing URL webpage into JSON + RDF.
Home-page: https://github.com/NeilGraham/urlscrub
Author: Neil Graham
Author-email: grahamneiln@gmail.com
License: UNKNOWN
Platform: UNKNOWN
Requires-Python: >=3.10
